{
  "name": "SAVY Admin — Dashboard",
  "short_name": "SAVY Admin",
  "description": "Tableau de bord admin SAVY — commandes, clients, revenus",
  "start_url": "/dashboard.html",
  "display": "standalone",
  "orientation": "any",
  "background_color": "#080F0A",
  "theme_color": "#080F0A",
  "lang": "fr",
  "icons": [
    {
      "src": "images/icon-192.png",
      "sizes": "192x192",
      "type": "image/png",
      "purpose": "any maskable"
    },
    {
      "src": "images/icon-512.png",
      "sizes": "512x512",
      "type": "image/png",
      "purpose": "any maskable"
    }
  ],
  "shortcuts": [
    {
      "name": "Commandes",
      "url": "/dashboard.html#orders",
      "icons": [{ "src": "images/icon-192.png", "sizes": "192x192" }]
    },
    {
      "name": "Revenus",
      "url": "/dashboard.html#revenue",
      "icons": [{ "src": "images/icon-192.png", "sizes": "192x192" }]
    }
  ]
}
